wdlkit/__init__.py
wdlkit/__main__.py
wdlkit/ast.py
wdlkit/formatter.py
wdlkit/templates/call.wdl
wdlkit/templates/command.wdl
wdlkit/templates/conditional.wdl
wdlkit/templates/declarations.wdl
wdlkit/templates/document.wdl
wdlkit/templates/imports.wdl
wdlkit/templates/inputs.wdl
wdlkit/templates/meta.wdl
wdlkit/templates/outputs.wdl
wdlkit/templates/parameter_meta.wdl
wdlkit/templates/runtime.wdl
wdlkit/templates/scatter.wdl
wdlkit/templates/struct.wdl
wdlkit/templates/task.wdl
wdlkit/templates/workflow.wdl
wdlkit/templates/workflow_body.wdl
wdlkit/utils.py
wdlkit-0.1.5.dist-info/entry_points.txt
wdlkit-0.1.5.dist-info/WHEEL
wdlkit-0.1.5.dist-info/METADATA
wdlkit-0.1.5.dist-info/RECORD
