Metadata-Version: 2.1
Name: wdlkit
Version: 0.1.5
Summary: WDL development tools
License: MIT
Author: John Didion
Author-email: jdidion@dnanexus.com
Requires-Python: >=3.6.1,<4.0.0
Classifier: License :: OSI Approved :: MIT License
Classifier: Programming Language :: Python :: 3
Classifier: Programming Language :: Python :: 3.7
Classifier: Programming Language :: Python :: 3.8
Requires-Dist: autoclick (>=0.8.1,<0.9.0)
Requires-Dist: miniwdl (>=0.7.0,<0.8.0)
Requires-Dist: networkx (>=2.4,<3.0)
